ai_shell_agent/__init__.py
ai_shell_agent/ai.py
ai_shell_agent/chat_manager.py
ai_shell_agent/chat_state_manager.py
ai_shell_agent/config_manager.py
ai_shell_agent/console_manager.py
ai_shell_agent/errors.py
ai_shell_agent/llm.py
ai_shell_agent/paths.py
ai_shell_agent/settings.py
ai_shell_agent/styles.py
ai_shell_agent/texts.py
ai_shell_agent/tool_registry.py
ai_shell_agent/default_settings/default_settings.json
ai_shell_agent/prompts/__init__.py
ai_shell_agent/prompts/additional_prompt.py
ai_shell_agent/prompts/default_prompt.py
ai_shell_agent/prompts/prompts.py
ai_shell_agent/styles/default_style.json
ai_shell_agent/texts/en_texts.json
ai_shell_agent/toolsets/__init__.py
ai_shell_agent/toolsets/toolsets.py
ai_shell_agent/toolsets/aider/__init__.py
ai_shell_agent/toolsets/aider/prompts.py
ai_shell_agent/toolsets/aider/settings.py
ai_shell_agent/toolsets/aider/texts.py
ai_shell_agent/toolsets/aider/toolset.py
ai_shell_agent/toolsets/aider/default_settings/default_settings.json
ai_shell_agent/toolsets/aider/integration/__init__.py
ai_shell_agent/toolsets/aider/integration/integration.py
ai_shell_agent/toolsets/aider/tools/schemas.py
ai_shell_agent/toolsets/aider/tools/tools.py
ai_shell_agent/toolsets/cognitive/__init__.py
ai_shell_agent/toolsets/cognitive/prompts.py
ai_shell_agent/toolsets/cognitive/settings.py
ai_shell_agent/toolsets/cognitive/texts.py
ai_shell_agent/toolsets/cognitive/toolset.py
ai_shell_agent/toolsets/cognitive/default_settings/default_settings.json
ai_shell_agent/toolsets/files/__init__.py
ai_shell_agent/toolsets/files/prompts.py
ai_shell_agent/toolsets/files/settings.py
ai_shell_agent/toolsets/files/state.py
ai_shell_agent/toolsets/files/texts.py
ai_shell_agent/toolsets/files/toolset.py
ai_shell_agent/toolsets/files/default_settings/default_settings.json
ai_shell_agent/toolsets/files/integration/__init__.py
ai_shell_agent/toolsets/files/integration/find_logic.py
ai_shell_agent/toolsets/files/tools/__init__.py
ai_shell_agent-0.2.2.dist-info/licenses/LICENSE
ai_shell_agent-0.2.2.dist-info/METADATA
ai_shell_agent-0.2.2.dist-info/WHEEL
ai_shell_agent-0.2.2.dist-info/entry_points.txt
ai_shell_agent-0.2.2.dist-info/top_level.txt
ai_shell_agent-0.2.2.dist-info/RECORD
