Metadata-Version: 2.4
Name: ai-shell-agent
Version: 0.2.2
Summary: AI agent in your Terminal / CMD / Console - an AI application that helps perform tasks by writing and executing terminal commands with user supervision and by answering questions.
Home-page: https://github.com/laelhalawani/ai-shell-agent
Author: Lael Al-Halawani
Author-email: Lael Al-Halawani <laelhalawani@gmail.com>
License: MIT License
Project-URL: Homepage, https://github.com/laelhalawani/ai-shell-agent
Classifier: Programming Language :: Python :: 3
Classifier: License :: OSI Approved :: MIT License
Classifier: Operating System :: OS Independent
Requires-Python: >=3.11
License-File: LICENSE
Requires-Dist: python-dotenv==1.0.1
Requires-Dist: langchain_openai==0.3.2
Requires-Dist: langchain_google_genai==2.1.2
Requires-Dist: langchain_experimental==0.3.4
Requires-Dist: prompt_toolkit==3.0.50
Requires-Dist: aider-chat==0.79.2
Requires-Dist: gitpython==3.1.44
Requires-Dist: watchfiles==1.0.4
Requires-Dist: rich==13.9.4
Requires-Dist: rapidfuzz==3.13.0
Dynamic: author
Dynamic: home-page
Dynamic: license-file
Dynamic: requires-python
